{"title":"Donut Chart","markdown":{"headingText":"Donut Chart","containsRefs":false,"markdown":"\n## Datos \n\nLo primero será crear un `data.table` con datos simulados. En este caso son 2 categorías.\n\n-   Sexo que irá en la torta\n\n-   Grupo que irá en facets\n\n-   N que son recuentos\n\n``` r\nlibrary(data.table)\nlibrary(scales)\nlibrary(ggplot2)\nlibrary(forcats)\n\n# Partimos con data numerica de cantidades\ngdata <- data.table(\n    SEXO = rep(c(\"Hombre\", \"Mujer\"), 4),\n    GRUPO = rep(c(\"D\", \"C\", \"B\", \"A\"), each = 2),\n    N = c(2220698, 1713396, 1381339, 1274634, 2841801, 3748242, 1292953, 1743318)\n)\n\nprint(gdata, row.names = FALSE)\n```\n\n```         \n##    SEXO  GRUPO       N\n##  <char> <char>   <num>\n##  Hombre      D 2220698\n##   Mujer      D 1713396\n##  Hombre      C 1381339\n##   Mujer      C 1274634\n##  Hombre      B 2841801\n##   Mujer      B 3748242\n##  Hombre      A 1292953\n##   Mujer      A 1743318\n```\n\n## Data Management \n\nAhora necesitamos crear los minimos y máximos de los porcentajes de N respecto de cada GRUPO. La razón es que este gráfico se crea usando rectangulos de un tamaño definido por los porcentajes. Hacemos un pequeño data management.\n\n``` r\n# Calculamos el porcentaje\ngdata[, PCT := N/sum(N), GRUPO]\n\n# El valor maximo de cada geom_rect\ngdata[, YMAX := cumsum(PCT), GRUPO]\n\n# El valor mínimo\ngdata[, YMIN := shift(YMAX, type = 'lag')]\ngdata[, YMIN := ifelse(YMAX != 1, 0, YMIN)]\n\n# Indice entre Mujer/Hombre\ngdata[, FEM := round(PCT/YMIN, 2)]\ngdata[, FEM := ifelse(FEM == Inf, NA, FEM)]\n\nprint(as.data.frame(gdata), row.names = FALSE)\n```\n\n```         \n##    SEXO GRUPO       N       PCT      YMAX      YMIN  FEM\n##  Hombre     D 2220698 0.5644751 0.5644751 0.0000000   NA\n##   Mujer     D 1713396 0.4355249 1.0000000 0.5644751 0.77\n##  Hombre     C 1381339 0.5200877 0.5200877 0.0000000   NA\n##   Mujer     C 1274634 0.4799123 1.0000000 0.5200877 0.92\n##  Hombre     B 2841801 0.4312265 0.4312265 0.0000000   NA\n##   Mujer     B 3748242 0.5687735 1.0000000 0.4312265 1.32\n##  Hombre     A 1292953 0.4258358 0.4258358 0.0000000   NA\n##   Mujer     A 1743318 0.5741642 1.0000000 0.4258358 1.35\n```\n\n## Theme \n\nYa con esto el grafico, pero primero el theme que suelo usar. Producto del mismo tuve que pasar muchos elementos a `element_blank()` .\n\n``` r\n# Mi tema\nolito_theme <- function(){\n    theme_bw() %+replace%  \n        theme(\n            axis.title.y = element_text(margin = margin(r = 6), \n                                        size = 14, hjust = 0, color = \"gray30\",\n                                        angle = 90),\n            axis.title.x = element_text(margin = margin(t = 8), \n                                        size = 14, hjust = 0, color = \"gray30\"),\n            axis.text.x.top = element_blank(),\n            axis.text.y.right = element_blank(),\n            axis.text.x = element_text(size = 12, color = \"gray30\"), \n            axis.text.y = element_text(size = 12, color = \"gray30\", hjust = 1),\n            axis.line = element_line(color =\"gray30\", linewidth = 0.5),\n            axis.ticks.length.x.top = unit(0, \"cm\"),\n            axis.ticks.length.y.right = unit(0, \"cm\"),\n            axis.ticks.length.y = unit(.15, \"cm\"),\n            axis.ticks.length.x = unit(.15, \"cm\"),\n            panel.grid.major.x = element_line(color = \"gray85\"),\n            panel.grid.major.y = element_line(color = \"gray85\"),\n            panel.grid.minor.y = element_blank(),\n            panel.grid.minor.x = element_blank(),\n            panel.background = element_rect(color = \"white\", fill = 'grey98', linewidth = 0.1),\n            legend.position = \"top\", \n            legend.margin = margin(b = 0),\n            legend.justification = \"right\",\n            legend.title = element_text(size = 14, color = \"gray30\"),\n            legend.text = element_text(size = 13, color = \"gray30\"),\n            strip.text.x = element_text(size = 12),\n            strip.text.y = element_text(size = 12, angle = 270)\n        )\n}\n```\n\n## Grafico \n\n``` r\ng <- ggplot(gdata, aes(ymax=YMAX, ymin=YMIN, xmax=4, xmin=3, fill=SEXO)) +\n    geom_rect(color = 'grey30') +\n    facet_grid(cols = vars(forcats::fct_rev(GRUPO))) +\n    scale_fill_manual(values = c(\"steelblue\",\"hotpink2\"))  +\n    coord_polar(theta = \"y\") + xlim(c(1, 4)) +\n    olito_theme() +\n    geom_text(aes(x = 3.5, y = (YMIN + YMAX) / 2, \n                  label = scales::percent(PCT, accuracy = 1)), \n              color = \"white\", size = 5, fontface = 'bold' ,\n              show.legend = FALSE) +\n    theme(axis.text.x = element_blank(), axis.text.y = element_blank(),\n          axis.ticks = element_blank(), panel.grid.major.x = element_blank(), \n          panel.grid.major.y = element_blank(), panel.border = element_blank(),\n          strip.background = element_blank(), panel.background = element_blank(),\n          axis.line = element_blank(), axis.title.x = element_blank(),\n          axis.title.y = element_blank(), strip.text.x = element_blank() ) +\n    labs(fill = \"Sexo\") +\n    geom_text(x = 0.5, y = 0.5, label = gdata$GRUPO, \n             color = \"grey30\", size = 12, fontface = \"bold\") +\n    geom_text(x = 1.5, y = 0.5, label = gdata$FEM, \n              color = \"grey30\", size = 8, fontface = \"bold\")\n\nggsave(\"donut.png\", plot = g, width = 1500, height = 400, \n       units = \"px\", dpi = 120, scale = 120/96)\n```\n\nY Voila!\n\n![](donut.png)\n","srcMarkdownNoYaml":""},"formats":{"html":{"identifier":{"display-name":"HTML","target-format":"html","base-format":"html"},"execute":{"fig-width":7,"fig-height":5,"fig-format":"retina","fig-dpi":96,"df-print":"default","error":false,"eval":true,"cache":null,"freeze":false,"echo":true,"output":true,"warning":true,"include":true,"keep-md":false,"keep-ipynb":false,"ipynb":null,"enabled":null,"daemon":null,"daemon-restart":false,"debug":false,"ipynb-filters":[],"ipynb-shell-interactivity":null,"plotly-connected":true,"engine":"markdown"},"render":{"keep-tex":false,"keep-typ":false,"keep-source":false,"keep-hidden":false,"prefer-html":false,"output-divs":true,"output-ext":"html","fig-align":"default","fig-pos":null,"fig-env":null,"code-fold":"none","code-overflow":"scroll","code-link":false,"code-line-numbers":false,"code-tools":false,"tbl-colwidths":"auto","merge-includes":true,"inline-includes":false,"preserve-yaml":false,"latex-auto-mk":true,"latex-auto-install":true,"latex-clean":true,"latex-min-runs":1,"latex-max-runs":10,"latex-makeindex":"makeindex","latex-makeindex-opts":[],"latex-tlmgr-opts":[],"latex-input-paths":[],"latex-output-dir":null,"link-external-icon":false,"link-external-newwindow":false,"self-contained-math":false,"format-resources":[],"notebook-links":true},"pandoc":{"standalone":true,"wrap":"none","default-image-extension":"png","to":"html","toc":true,"css":["../styles.css"],"output-file":"readme.html"},"language":{"toc-title-document":"Table of contents","toc-title-website":"On this page","related-formats-title":"Other Formats","related-notebooks-title":"Notebooks","source-notebooks-prefix":"Source","other-links-title":"Other Links","code-links-title":"Code Links","launch-dev-container-title":"Launch Dev Container","launch-binder-title":"Launch Binder","article-notebook-label":"Article Notebook","notebook-preview-download":"Download Notebook","notebook-preview-download-src":"Download Source","notebook-preview-back":"Back to Article","manuscript-meca-bundle":"MECA Bundle","section-title-abstract":"Abstract","section-title-appendices":"Appendices","section-title-footnotes":"Footnotes","section-title-references":"References","section-title-reuse":"Reuse","section-title-copyright":"Copyright","section-title-citation":"Citation","appendix-attribution-cite-as":"For attribution, please cite this work as:","appendix-attribution-bibtex":"BibTeX citation:","appendix-view-license":"View License","title-block-author-single":"Author","title-block-author-plural":"Authors","title-block-affiliation-single":"Affiliation","title-block-affiliation-plural":"Affiliations","title-block-published":"Published","title-block-modified":"Modified","title-block-keywords":"Keywords","callout-tip-title":"Tip","callout-note-title":"Note","callout-warning-title":"Warning","callout-important-title":"Important","callout-caution-title":"Caution","code-summary":"Code","code-tools-menu-caption":"Code","code-tools-show-all-code":"Show All Code","code-tools-hide-all-code":"Hide All Code","code-tools-view-source":"View Source","code-tools-source-code":"Source Code","tools-share":"Share","tools-download":"Download","code-line":"Line","code-lines":"Lines","copy-button-tooltip":"Copy to Clipboard","copy-button-tooltip-success":"Copied!","repo-action-links-edit":"Edit this page","repo-action-links-source":"View source","repo-action-links-issue":"Report an issue","back-to-top":"Back to top","search-no-results-text":"No results","search-matching-documents-text":"matching documents","search-copy-link-title":"Copy link to search","search-hide-matches-text":"Hide additional matches","search-more-match-text":"more match in this document","search-more-matches-text":"more matches in this document","search-clear-button-title":"Clear","search-text-placeholder":"","search-detached-cancel-button-title":"Cancel","search-submit-button-title":"Submit","search-label":"Search","toggle-section":"Toggle section","toggle-sidebar":"Toggle sidebar navigation","toggle-dark-mode":"Toggle dark mode","toggle-reader-mode":"Toggle reader mode","toggle-navigation":"Toggle navigation","crossref-fig-title":"Figure","crossref-tbl-title":"Table","crossref-lst-title":"Listing","crossref-thm-title":"Theorem","crossref-lem-title":"Lemma","crossref-cor-title":"Corollary","crossref-prp-title":"Proposition","crossref-cnj-title":"Conjecture","crossref-def-title":"Definition","crossref-exm-title":"Example","crossref-exr-title":"Exercise","crossref-ch-prefix":"Chapter","crossref-apx-prefix":"Appendix","crossref-sec-prefix":"Section","crossref-eq-prefix":"Equation","crossref-lof-title":"List of Figures","crossref-lot-title":"List of Tables","crossref-lol-title":"List of Listings","environment-proof-title":"Proof","environment-remark-title":"Remark","environment-solution-title":"Solution","listing-page-order-by":"Order By","listing-page-order-by-default":"Default","listing-page-order-by-date-asc":"Oldest","listing-page-order-by-date-desc":"Newest","listing-page-order-by-number-desc":"High to Low","listing-page-order-by-number-asc":"Low to High","listing-page-field-date":"Date","listing-page-field-title":"Title","listing-page-field-description":"Description","listing-page-field-author":"Author","listing-page-field-filename":"File Name","listing-page-field-filemodified":"Modified","listing-page-field-subtitle":"Subtitle","listing-page-field-readingtime":"Reading Time","listing-page-field-wordcount":"Word Count","listing-page-field-categories":"Categories","listing-page-minutes-compact":"{0} min","listing-page-category-all":"All","listing-page-no-matches":"No matching items","listing-page-words":"{0} words","listing-page-filter":"Filter","draft":"Draft"},"metadata":{"lang":"en","fig-responsive":true,"quarto-version":"1.6.40","editor":"visual","theme":"cosmo","toc-title":"Contenido"},"extensions":{"book":{"multiFile":true}}}},"projectFormats":["html"]}